setup.py
JGVutils/JGVutils.py
JGVutils/__init__.py
JGVutils.egg-info/PKG-INFO
JGVutils.egg-info/SOURCES.txt
JGVutils.egg-info/dependency_links.txt
JGVutils.egg-info/requires.txt
JGVutils.egg-info/top_level.txt