Metadata-Version: 2.1
Name: JGVutils
Version: 1.0.5.0
Summary: Utils for Python
Home-page: https://github.com/JuanGomezVilla/JGVutils
Author: JuanGV
License: MIT LICENSE
